classiq/__init__.py
classiq/_analyzer_extras/__init__.py
classiq/_analyzer_extras/_ipywidgets_async_extension.py
classiq/_analyzer_extras/interactive_hardware.py
classiq/_internals/__init__.py
classiq/_internals/api_wrapper.py
classiq/_internals/async_utils.py
classiq/_internals/authentication/__init__.py
classiq/_internals/authentication/auth0.py
classiq/_internals/authentication/authentication.py
classiq/_internals/authentication/authorization_code.py
classiq/_internals/authentication/authorization_flow.py
classiq/_internals/authentication/device.py
classiq/_internals/authentication/hybrid_flow.py
classiq/_internals/authentication/password_manager.py
classiq/_internals/authentication/token_manager.py
classiq/_internals/client.py
classiq/_internals/config.py
classiq/_internals/help.py
classiq/_internals/host_checker.py
classiq/_internals/jobs.py
classiq/_internals/logger.py
classiq/_internals/type_validation.py
classiq/analyzer/__init__.py
classiq/analyzer/analyzer.py
classiq/analyzer/analyzer_utilities.py
classiq/analyzer/rb.py
classiq/analyzer/show_interactive_hack.py
classiq/analyzer/url_utils.py
classiq/applications/__init__.py
classiq/applications/chemistry/__init__.py
classiq/applications/chemistry/hartree_fock.py
classiq/applications/chemistry/mapping.py
classiq/applications/chemistry/op_utils.py
classiq/applications/chemistry/problems.py
classiq/applications/chemistry/ucc.py
classiq/applications/chemistry/z2_symmetries.py
classiq/applications/combinatorial_helpers/__init__.py
classiq/applications/combinatorial_helpers/allowed_constraints.py
classiq/applications/combinatorial_helpers/arithmetic/__init__.py
classiq/applications/combinatorial_helpers/arithmetic/arithmetic_expression.py
classiq/applications/combinatorial_helpers/arithmetic/isolation.py
classiq/applications/combinatorial_helpers/combinatorial_problem_utils.py
classiq/applications/combinatorial_helpers/encoding_mapping.py
classiq/applications/combinatorial_helpers/encoding_utils.py
classiq-0.105.0.dist-info/licenses/LICENSE.txt
classiq-0.105.0.dist-info/WHEEL
classiq-0.105.0.dist-info/METADATA
classiq-0.105.0.dist-info/RECORD
